upright/fiducials.py
upright/geometry.py
upright/query.py
upright/upright.py
sarahwallingbell_test_package-0.0.1.dist-info/LICENSE
sarahwallingbell_test_package-0.0.1.dist-info/METADATA
sarahwallingbell_test_package-0.0.1.dist-info/WHEEL
sarahwallingbell_test_package-0.0.1.dist-info/top_level.txt
sarahwallingbell_test_package-0.0.1.dist-info/RECORD
